Metadata-Version: 2.1
Name: ninchanese-cjklib
Version: 0.4.1
Summary: Han character library for CJKV languages
Home-page: http://cjklib.org
Author: Christoph Burgmer
Author-email: cburgmer@ira.uka.de
License: LGPL
Platform: UNKNOWN
Classifier: Topic :: Text Processing :: Linguistic
Classifier: Environment :: Console
Classifier: Intended Audience :: Developers
Classifier: Intended Audience :: Education
Classifier: Development Status :: 5 - Production/Stable
Classifier: Operating System :: OS Independent
Classifier: Programming Language :: Python
Classifier: License :: OSI Approved :: GNU Library or Lesser General Public License (LGPL)
Classifier: Natural Language :: Chinese (Simplified)
Classifier: Natural Language :: Chinese (Traditional)
Classifier: Natural Language :: Japanese
Classifier: Natural Language :: Korean
Classifier: Natural Language :: Vietnamese
Requires-Dist: SQLAlchemy (>=0.9)
